bridgic/llms/openai_like/__init__.py
bridgic/llms/openai_like/openai_like_llm.py
bridgic_llms_openai_like-0.1.0.dist-info/METADATA
bridgic_llms_openai_like-0.1.0.dist-info/WHEEL
bridgic_llms_openai_like-0.1.0.dist-info/licenses/LICENSE
bridgic_llms_openai_like-0.1.0.dist-info/RECORD
